london_unified_prayer_times/__init__.py
london_unified_prayer_times/cache.py
london_unified_prayer_times/cli.py
london_unified_prayer_times/config.py
london_unified_prayer_times/constants.py
london_unified_prayer_times/default_config.json
london_unified_prayer_times/london_unified_prayer_times.py
london_unified_prayer_times/query.py
london_unified_prayer_times/remote_data.py
london_unified_prayer_times/report.py
london_unified_prayer_times/timetable.py
london_unified_prayer_times-1.2.9.dist-info/AUTHORS.rst
london_unified_prayer_times-1.2.9.dist-info/LICENSE
london_unified_prayer_times-1.2.9.dist-info/METADATA
london_unified_prayer_times-1.2.9.dist-info/WHEEL
london_unified_prayer_times-1.2.9.dist-info/entry_points.txt
london_unified_prayer_times-1.2.9.dist-info/top_level.txt
london_unified_prayer_times-1.2.9.dist-info/RECORD
