Metadata-Version: 2.1
Name: london-unified-prayer-times
Version: 1.2.9
Summary: A library for retrieving data from The London Unified Prayer Timetable.
Home-page: https://github.com/sshaikh/london_unified_prayer_times
Author: Shakil Shaikh
Author-email: sshaikh@users.noreply.github.com
License: GNU General Public License v3
Keywords: london_unified_prayer_times
Platform: UNKNOWN
Classifier: Development Status :: 5 - Production/Stable
Classifier: Intended Audience :: Developers
Classifier: License :: OSI Approved :: GNU General Public License v3 (GPLv3)
Classifier: Natural Language :: English
Classifier: Programming Language :: Python :: 3
Classifier: Programming Language :: Python :: 3.7
Classifier: Programming Language :: Python :: 3.8
Requires-Python: >=3.5
License-File: LICENSE
License-File: AUTHORS.rst
Requires-Dist: Click
Requires-Dist: click-default-group
Requires-Dist: jsonschema
Requires-Dist: python-dateutil
Requires-Dist: appdirs
Requires-Dist: tzlocal
Requires-Dist: humanize
Requires-Dist: beautifulsoup4
